acni/__init__.py
acni/_acni.py
acni-0.0.1.dist-info/LICENSE
acni-0.0.1.dist-info/METADATA
acni-0.0.1.dist-info/WHEEL
acni-0.0.1.dist-info/top_level.txt
acni-0.0.1.dist-info/RECORD
